README.md
setup.py
drf_dynamicfieldserializer.egg-info/PKG-INFO
drf_dynamicfieldserializer.egg-info/SOURCES.txt
drf_dynamicfieldserializer.egg-info/dependency_links.txt
drf_dynamicfieldserializer.egg-info/requires.txt
drf_dynamicfieldserializer.egg-info/top_level.txt
dynamicfield_serializer/__init__.py
dynamicfield_serializer/serializers.py