Metadata-Version: 1.2
Name: drf-dynamicfieldserializer
Version: 0.1
Summary: SalesForce wrapper
Home-page: https://github.com/bzdvdn/drf-dynamicfieldserializer.git
Author: bzdvdn
Author-email: bzdv.dn@gmail.com
License: MIT
Platform: UNKNOWN
Requires-Python: >=3.6
